firebase_main/__init__.py
firebase_main/cli.py
firebase_main-1.2.4.dist-info/METADATA
firebase_main-1.2.4.dist-info/WHEEL
firebase_main-1.2.4.dist-info/entry_points.txt
firebase_main-1.2.4.dist-info/top_level.txt
firebase_main-1.2.4.dist-info/RECORD
