Metadata-Version: 2.1
Name: firebase-main
Version: 1.2.4
Home-page: https://github.com/ByteBreach/firebase-main
Author: MrFidal
Author-email: mrfidal@proton.me
Keywords: mrfidal,firebase,fidal,fidal plamaprambil,firebase-tools,firebase-deploy,firebase-init,firebase-functions,python,firebase main,deployment,cloud,serverless
Classifier: Programming Language :: Python :: 3
Classifier: License :: OSI Approved :: MIT License
Classifier: Operating System :: OS Independent
Requires-Python: >=3.6
Requires-Dist: colorama
Requires-Dist: trackdir
